setup.py
s3proxy/__init__.py
s3proxy.egg-info/PKG-INFO
s3proxy.egg-info/SOURCES.txt
s3proxy.egg-info/dependency_links.txt
s3proxy.egg-info/entry_points.txt
s3proxy.egg-info/pbr.json
s3proxy.egg-info/requires.txt
s3proxy.egg-info/top_level.txt