Metadata-Version: 1.1
Name: s3proxy
Version: 0.5.1
Summary: HTTP Proxy for S3 buckets
Home-page: https://github.com/reversefold/python-s3proxy
Author: Justin Patrin
Author-email: papercrane@reversefold.com
License: License :: OSI Approved :: MIT License
Download-URL: https://github.com/reversefold/python-s3proxy/tarball/release/0.5.1
Platform: UNKNOWN
